{"skeleton":{"hash":"kNvBfNcMIUcdApHi5v3oQSdhZK8","spine":"3.8.99","x":-143.5,"y":-89,"width":287,"height":178,"images":"./img/","audio":""},"bones":[{"name":"root"},{"name":"新建文件夹/电_00","parent":"root","rotation":90,"x":-8.08,"y":10.61,"scaleX":1.1738,"scaleY":2.1459}],"slots":[{"name":"新建文件夹/发电机","bone":"root"},{"name":"新建文件夹/电_00","bone":"新建文件夹/电_00"},{"name":"Glow","bone":"root","blend":"additive"}],"skins":[{"name":"default","attachments":{"Glow":{"Glow":{"color":"0095ffff","scaleX":2.5125,"scaleY":1.3943,"width":180,"height":180}},"新建文件夹/电_00":{"新建文件夹/电_00":{"width":200,"height":200},"新建文件夹/电_01":{"width":200,"height":200},"新建文件夹/电_02":{"width":200,"height":200},"新建文件夹/电_03":{"width":200,"height":200},"新建文件夹/电_04":{"width":200,"height":200},"新建文件夹/电_05":{"width":200,"height":200},"新建文件夹/电_06":{"width":200,"height":200},"新建文件夹/电_07":{"width":200,"height":200},"新建文件夹/电_08":{"width":200,"height":200},"新建文件夹/电_09":{"width":200,"height":200},"新建文件夹/电_10":{"width":200,"height":200},"新建文件夹/电_11":{"width":200,"height":200},"新建文件夹/电_12":{"width":200,"height":200},"新建文件夹/电_13":{"width":200,"height":200},"新建文件夹/电_14":{"width":200,"height":200},"新建文件夹/电_15":{"width":200,"height":200},"新建文件夹/电_16":{"width":200,"height":200},"新建文件夹/电_17":{"width":200,"height":200}}}}],"animations":{"animation":{"slots":{"Glow":{"attachment":[{"name":"Glow"},{"time":0.0667,"name":null},{"time":0.1333,"name":"Glow"},{"time":0.2,"name":null},{"time":0.2667,"name":"Glow"},{"time":0.3333,"name":null},{"time":0.4,"name":"Glow"},{"time":0.4667,"name":null},{"time":0.5333,"name":"Glow"},{"time":0.6,"name":null},{"time":0.6667,"name":"Glow"},{"time":0.7333,"name":null},{"time":0.8667,"name":"Glow"},{"time":0.9333,"name":null},{"time":1,"name":"Glow"},{"time":1.0667,"name":null},{"time":1.1333,"name":"Glow"}]},"新建文件夹/电_00":{"attachment":[{"name":"新建文件夹/电_00"},{"time":0.0667,"name":"新建文件夹/电_01"},{"time":0.1333,"name":"新建文件夹/电_02"},{"time":0.2,"name":"新建文件夹/电_03"},{"time":0.2667,"name":"新建文件夹/电_04"},{"time":0.3333,"name":"新建文件夹/电_05"},{"time":0.4,"name":"新建文件夹/电_06"},{"time":0.4667,"name":"新建文件夹/电_07"},{"time":0.5333,"name":"新建文件夹/电_08"},{"time":0.6,"name":"新建文件夹/电_09"},{"time":0.6667,"name":"新建文件夹/电_10"},{"time":0.7333,"name":"新建文件夹/电_11"},{"time":0.8,"name":"新建文件夹/电_12"},{"time":0.8667,"name":"新建文件夹/电_13"},{"time":0.9333,"name":"新建文件夹/电_14"},{"time":1,"name":"新建文件夹/电_15"},{"time":1.0667,"name":"新建文件夹/电_16"},{"time":1.1333,"name":"新建文件夹/电_17"},{"time":1.2,"name":"新建文件夹/电_00"}]}}}}}